ddispatch/__init__.py
ddispatch/_dispatch.py
ddispatch/tests/test_dispatch.py
ddispatch-0.0.3.dist-info/licenses/LICENSE
ddispatch-0.0.3.dist-info/METADATA
ddispatch-0.0.3.dist-info/WHEEL
ddispatch-0.0.3.dist-info/top_level.txt
ddispatch-0.0.3.dist-info/RECORD
