Metadata-Version: 2.4
Name: ddispatch
Version: 0.0.3
Summary: Single generic function dispatch
Author-email: Michael Chow <mc_al_github@fastmail.com>
License: MIT License
Project-URL: homepage, https://github.com/machow/ddispatch
Keywords: data
Classifier: Programming Language :: Python :: 3.9
Classifier: Programming Language :: Python :: 3.10
Classifier: Programming Language :: Python :: 3.11
Classifier: Programming Language :: Python :: 3.12
Requires-Python: >=3.9
License-File: LICENSE
Provides-Extra: dev
Requires-Dist: pytest; extra == "dev"
Dynamic: license-file
